paygen/__init__.py
paygen/cli.py
paygen/gen.py
paygen-0.3.0.dist-info/METADATA
paygen-0.3.0.dist-info/WHEEL
paygen-0.3.0.dist-info/entry_points.txt
paygen-0.3.0.dist-info/RECORD
