Metadata-Version: 2.4
Name: paygen
Version: 0.3.0
Summary: A tool for generating web payloads
Author-email: Joao Figueiredo <joao@azulhq.com>
Requires-Python: >=3.13
Requires-Dist: faker>=37.1.0
Requires-Dist: hatchling>=1.27.0
Requires-Dist: numpy>=2.2.5
Requires-Dist: tqdm>=4.66.0
Requires-Dist: typer>=0.15.3
